celery_plus/__init__.py
celery_plus/ischeduler.py
celery_plus/utils/__init__.py
celery_plus/utils/time_util.py
celery_plus-0.0.6.dist-info/LICENSE
celery_plus-0.0.6.dist-info/METADATA
celery_plus-0.0.6.dist-info/WHEEL
celery_plus-0.0.6.dist-info/RECORD
